setup.py
cbarrera_distributions/Binomialdistribution.py
cbarrera_distributions/Gaussiandistribution.py
cbarrera_distributions/Generaldistribution.py
cbarrera_distributions/__init__.py
cbarrera_distributions.egg-info/PKG-INFO
cbarrera_distributions.egg-info/SOURCES.txt
cbarrera_distributions.egg-info/dependency_links.txt
cbarrera_distributions.egg-info/not-zip-safe
cbarrera_distributions.egg-info/top_level.txt